Workbook

Sheet Overview
C3: George — Asian Peptide Supplier Qualification
C5: Public-evidence screening converted into a controlled due-diligence programme
C6: Decision date: 20 August 2026 | Not a supplier approval or SAHPRA authorization
C8: DECISION SNAPSHOT
C10: Manufacturers screened | F10: Conditional Tier A | I10: Tier B manufacturers
C11: =COUNTA('Manufacturer Screen'!C9:C18) | F11: =COUNTIF('Manufacturer Screen'!P9:P18,"A") | I11: =COUNTIF('Manufacturer Screen'!P9:P18,"B")
C12: 10 entities | F12: RFI priority only | I12: Enhanced diligence required
C14: Laboratories screened | F14: Open RFI items | I14: No-go risks
C15: =COUNTA('Laboratory Screen'!C9:C12) | F15: =COUNTIFS('RFI Tracker'!K9:K86,"<>Closed",'RFI Tracker'!K9:K86,"<>Not Applicable",'RFI Tracker'!K9:K86,"<>") | I15: =COUNTIF('Risk & No-Go'!L9:L28,"No-Go")
C16: 4 sites/networks | F16: Live tracker | I16: Automatic hold criteria
C19: FIRST-WAVE DECISIONS
C21: # | D21: Decision | E21: Required action | F21: Gate
C22: 1 | D22: Issue manufacturer RFIs | E22: ScinoPharm, Hybio, Piramal and WuXi, plus one molecule-matched API comparator. | F22: RFI issuance only; no PO or supply award.
C23: 2 | D23: Issue laboratory RFIs | E23: Vimta first; SGS Shanghai and Eurofins Kyoto/Kobe in parallel. | F23: Method/site qualification and blind split-sample exercise required.
C24: 3 | D24: Keep Intertek bounded | E24: Do not use Mumbai as sole release laboratory on current evidence. | F24: Current verified accreditation scope is non-pharmaceutical.
C25: 4 | D25: Commission SA regulatory gap review | E25: Fix applicant, importer, licences, dossier/LoA, testing/release, GDP, PV and recall roles. | F25: No commercial or registration shipment until lawful pathway is confirmed.
C26: 5 | D26: Run 90-day qualification | E26: Document review, technical assessment, audits, laboratory exercise, CAPA and board decision. | F26: Re-score using confidential evidence; public scores expire at the decision board.
C29: WORKBOOK CONTENTS
C31: Manufacturer Screen
C32: Laboratory Screen
C33: RFI Tracker
C34: 90-Day Plan
C35: Risk & No-Go
C36: Source Register
C39: USE AND CONTROL NOTE
C41: This workbook is a controlled prequalification tool. Tier and score results reflect public evidence only. No supplier, site, product, method, laboratory, batch or transport lane may be approved solely from this file. Final disposition requires regulator-verifiable primary documents, site and method audits, validated testing, quality/technical agreements, a lawful SAHPRA route and formal cross-functional approval.

Sheet Manufacturer Screen
C3: Asian Peptide Manufacturer Screen
C5: Transparent 100-point public-evidence comparison; Tier A is diligence priority, not approval
C6: Blue = hardcoded evidence input | Black = formula | Scores must be replaced after confidential diligence
C8: ID | D8: Manufacturer | E8: Country | F8: Principal Site Chain | G8: Supply Level | H8: Reg 25 | I8: Peptide 20 | J8: Analyt/DI 15 | K8: Market 15 | L8: Resilience 15 | M8: Transparency 10 | N8: Total | O8: Override | P8: Tier | Q8: Evidenced Markets | R8: Adverse History / Unknowns | S8: Screening Decision
C9: M01 | D9: WuXi TIDES / WuXi STA (WuXi AppTec) | E9: China | F9: Changzhou and Taixing, Jiangsu (peptide API); Wuxi City, Jiangsu (sterile drug product) | G9: API/DS; separate sterile DP/fill-finish | H9: 19 | I9: 19 | J9: 11 | K9: 12 | L9: 6 | M9: 5 | N9: =SUM(H9:M9) | O9: No | P9: =IF(O9="Critical","C",IF(N9>=75,"A",IF(N9>=55,"B","C"))) | Q9: United States (company-reported 2025 FDA surveillance/PAI); EU, Japan, South Korea, China and Brazil signals require primary-record confirmation; South Africa: Unknown | R9: Incomplete 2023 Wuxi 483 artifact; new Taixing ramp; June 2026 US Section 1260H designation remains under enjoined, pending litigation and is geopolitical, not a GMP finding. | S9: Enhanced RFI and separate API-versus-fill-finish audits; no award.
C10: M02 | D10: Sinopep-Allsino Biopharmaceutical Co., Ltd. | E10: China | F10: Lianyungang, Jiangsu (principal peptide API and claimed finished dose) | G10: API/DS strongest; sterile DP conditional; no device qualification | H10: 16 | I10: 18 | J10: 9 | K10: 10 | L10: 6 | M10: 3 | N10: =SUM(H10:M10) | O10: No | P10: =IF(O10="Critical","C",IF(N10>=75,"A",IF(N10>=55,"B","C"))) | Q10: China; US FDA inspection/DMF evidence; issuer-reported sales to India/Canada and region-level Europe; PMDA list entry; MFDS/ANVISA claims unverified; South Africa: Unknown | R10: CSRC Decision [2025] 148 found materially false financial disclosure and imposed RMB47.4 million company fine; governance/data-reliability red flag, not a GMP finding. | S10: Enhanced RFI focused on API; governance remediation and raw-data audit are gates.
C11: M03 | D11: Hybio Pharmaceutical Co., Ltd. | E11: China | F11: Wuhan (peptide API); Pingshan, Shenzhen (sterile DP/prefilled pen) | G11: API/DS plus evidenced sterile/prefilled DP chain | H11: 21 | I11: 19 | J11: 10 | K11: 14 | L11: 6 | M11: 3 | N11: =SUM(H11:M11) | O11: No | P11: =IF(O11="Critical","C",IF(N11>=75,"A",IF(N11>=55,"B","C"))) | Q11: US (FDA-approved liraglutide ANDA chain); China; EDQM/Europe API signal; Brazil; issuer-reported Chile, Pakistan, Indonesia, Thailand and Vietnam; South Africa: Unknown | R11: 2019 somatostatin assay failure and disclosure delay; Spanish atosiban authorization revoked in 2024; unresolved 2025 customs penalty reference; device chain opaque. | S11: Priority enhanced RFI; audit API and sterile/device chain separately. Tier B because adverse-history closure and current certificates are unresolved.
C12: M04 | D12: CPC Scientific / Medtide (Hangzhou) | E12: China | F12: Qiantang, Hangzhou (commercial peptide API); Rocklin alternate not yet evidenced operational/approved | G12: API/DS only on public evidence | H12: 15 | I12: 18 | J12: 10 | K12: 12 | L12: 5 | M12: 3 | N12: =SUM(H12:M12) | O12: No | P12: =IF(O12="Critical","C",IF(N12>=75,"A",IF(N12>=55,"B","C"))) | Q12: US; China; company-reported Germany/EU, Australia and South Korea; South Africa: Unknown | R12: 2012 FDA registration/listing warning letter; 2024 validation/equipment-qualification observations; 2026 483 contents/classification unavailable. | S12: RFI only; full 2024/2026 FDA packages and remediation effectiveness are hard gates.
C13: M05 | D13: Piramal Pharma Solutions, Turbhe | E13: India | F13: Turbhe, Navi Mumbai (peptide API); Lexington, US is separate sterile DP site | G13: API/DS; Turbhe is not evidenced as sterile DP | H13: 21 | I13: 17 | J13: 9 | K13: 13 | L13: 6 | M13: 4 | N13: =SUM(H13:M13) | O13: No | P13: =IF(O13="Critical","C",IF(N13>=75,"A",IF(N13>=55,"B","C"))) | Q13: US inspection/supply evidence; WHO-prequalified oxytocin and carbetocin API; EDQM-linked oxytocin evidence; South Africa: no Turbhe-specific linkage found | R13: Six FDA observations included quality-unit, repeated deviation, complaint, cleaning, batch-record and temperature-control deficiencies. | S13: Priority RFI for WHO-backed products; require FDA CAPA effectiveness and lane challenge before audit closure.
C14: M06 | D14: Shilpa Pharma Lifesciences / Shilpa Medicare | E14: India | F14: Raichur Units I/II (API); Jadcherla Unit IV (separate finished dose) | G14: API/DS; sterile DP not peptide-qualified and enforcement-affected | H14: 17 | I14: 16 | J14: 8 | K14: 11 | L14: 6 | M14: 4 | N14: =SUM(H14:M14) | O14: No | P14: =IF(O14="Critical","C",IF(N14>=75,"A",IF(N14>=55,"B","C"))) | Q14: EDQM CEP signals for desmopressin/octreotide; US inspection/DMF claim; Japan and Brazil inspection signals; South Africa: Unknown | R14: Raichur Unit I 2025 VAI; Jadcherla finished-dose 2020 FDA warning letter and unresolved public Import Alert 66-40 status. | S14: RFI for a CEP-backed API only; exclude Jadcherla from proposed chain absent verified enforcement closure and peptide-specific qualification.
C15: M07 | D15: PeptiStar Inc. | E15: Japan | F15: Settsu, Osaka single campus (R&D and Manufacturing Buildings 1/2) | G15: Non-sterile API/DS only | H15: 11 | I15: 17 | J15: 10 | K15: 5 | L15: 7 | M15: 6 | N15: =SUM(H15:M15) | O15: No | P15: =IF(O15="Critical","C",IF(N15>=75,"A",IF(N15>=55,"B","C"))) | Q15: No specific regulated therapeutic country/site/product linkage publicly evidenced; South Africa: Unknown | R15: No public enforcement located, but absence is not proof of a clean history; ownership/control and commercial batch history are incomplete. | S15: Confidential RFI and audit candidate only after Japanese licence/GMP and customer-authorized dossier evidence.
C16: M08 | D16: Ajinomoto Bio-Pharma Services (Japan) | E16: Japan | F16: Tokai, Mie (candidate AJIPHASE); Osaka/GeneDesign; Kawasaki is separate API/R&D context | G16: API/DS platform; no current in-group sterile DP | H16: 12 | I16: 18 | J16: 8 | K16: 5 | L16: 7 | M16: 5 | N16: =SUM(H16:M16) | O16: No | P16: =IF(O16="Critical","C",IF(N16>=75,"A",IF(N16>=55,"B","C"))) | Q16: No named therapeutic-peptide market linked to Tokai/Osaka; US AJIPHASE approval disclosure appears oligonucleotide; South Africa: Unknown | R16: Kawasaki 2025 FDA 483/VAI signal for investigations, document control and material compatibility; not automatically attributable to Tokai/Osaka. | S16: Technology-fit RFI only; require precise legal/site flow and independently verified GMP evidence before audit.
C17: M09 | D17: HLB PEP Co., Ltd. | E17: South Korea | F17: Jangseong Plant 1 and Osong Plant 2 (peptide API); Gwangju is non-GMP/pilot | G17: API/DS only | H17: 16 | I17: 15 | J17: 8 | K17: 10 | L17: 6 | M17: 3 | N17: =SUM(H17:M17) | O17: No | P17: =IF(O17="Critical","C",IF(N17>=75,"A",IF(N17>=55,"B","C"))) | Q17: South Korea; active US Type II DMFs; reported Japan recognition and historical India export authorization; South Africa: Unknown | R17: Confirmed 2025 one-month MFDS suspension for missing 2022/2023 APQRs on two Jangseong products; closure/effectiveness package unavailable. | S17: RFI for a defined API only; APQR retrospective impact assessment and MFDS closure are hard gates.
C18: M10 | D18: ScinoPharm Taiwan, Ltd. | E18: Taiwan | F18: Tainan (peptide API, sterile fill-finish, packaging and cold-chain GDP); Changshu, China is separate | G18: API/DS plus TFDA-evidenced sterile DP and packaging | H18: 23 | I18: 18 | J18: 11 | K18: 14 | L18: 7 | M18: 6 | N18: =SUM(H18:M18) | O18: No | P18: =IF(O18="Critical","C",IF(N18>=75,"A",IF(N18>=55,"B","C"))) | Q18: United States (ANDA-linked glatiramer PFS); Taiwan; historical/current signals for Europe, Japan and Brazil; South Africa: Unknown | R18: Historical 2012 VAI reported secondarily and 2015 FDA 483/EIR indexed; current primary FDA classifications/CAPA not reviewed. | S18: Tier A for RFI priority only, conditional on historical FDA package, site genealogy, sterile assurance, supplier map and SAHPRA pathway.
C21: SCORING WEIGHTS AND INTERPRETATION
C23: Criterion | D23: Weight | E23: Interpretation
C24: Regulatory/site evidence | D24: 25 | E24: Exact legal entity, address, current licences/certificates, inspections, product/site scope and closure status.
C25: Peptide capability | D25: 20 | E25: Therapeutic GMP API/DS evidence; synthesis, purification, isolation and scale; sterile/device separately evidenced.
C26: Analytical/data integrity | D26: 15 | E26: Peptide control strategy, validation, reference standards, OOS/OOT/CAPA, audit trails and raw-data governance.
C27: Regulated-market/export | D27: 15 | E27: Named product/dossier/label/CEP/WHO linkage outweighs registration, filing or generic export claims.
C28: Resilience/traceability | D28: 15 | E28: Site/train redundancy, critical-material genealogy, dual sourcing, subcontractor visibility and qualified lanes.
C29: Transparency/adverse response | D29: 10 | E29: Complete records, root cause, CAPA effectiveness, recurrence prevention and consistent claims.

Sheet Laboratory Screen
C3: Independent Laboratory Qualification Screen
C5: Each site and method requires primary-scope verification, audit, method qualification and split-sample evidence
C6: No third-party laboratory substitutes for manufacturer GMP, registered specifications or authorized batch release
C8: ID | D8: Laboratory | E8: Country | F8: Site | G8: Score | H8: Tier | I8: Verified Evidence Boundary | J8: Peptide-Relevant Methods | K8: Preliminary Role | L8: Qualification Status | M8: RFI Owner | N8: Audit Status | O8: Split-Sample Result | P8: Final Disposition
C9: L01 | D9: SGS Shanghai Health Science Laboratory | E9: China | F9: Yishan Road, Shanghai | G9: 66 | H9: B | I9: CMA certificate includes site through 2029; claimed ISO/IEC 17025/CNAS scope annex not obtained; company reports 2024 FDA inspection with no 483, but official EIR/classification unavailable. | J9: Strong conditional E&L; potential LC-MS, HPLC/UPLC, residual solvents, elemental impurities, microbiology and sterility. Water, counter-ion, particulates, CCI and excursions not site-verified. | K9: Specialist/conditional RFI; not sole release laboratory. | L9: Not Started | N9: Not Started | O9: Not Run | P9: Hold
C10: L02 | D10: Eurofins Analytical Science Laboratories, Kyoto and Kobe | E10: Japan | F10: Kyoto and Kobe, Japan | G10: 64 | H10: B | I10: PMDA 2024 Kyoto compliant result for undisclosed application scope; Kyoto FDA 2024 Form 483 unresolved; no site ISO 17025 scope verified; Kobe authority unknown. | J10: Broad LC-MS sequence/identity, HPLC/UPLC, GC, KF, ICP, microbiology/sterility, particulates, stability, CCI and E&L potential; exact site/method allocation required. | K10: Specialist/conditional; site- and method-specific audit required. | L10: Not Started | N10: Not Started | O10: Not Run | P10: Hold
C11: L03 | D11: Vimta Labs Limited, Life Sciences Facility | E11: India | F11: Genome Valley, Hyderabad | G11: 70 | H11: B | I11: Current NABL ISO/IEC 17025 certificate through 2028 but annex absent; current WHO-prequalified QCL listing; exact-site FDA 2023 VAI; veterinary GMP stability scope through 2027. | J11: Strong conditional LC-MS/intact mass, HPLC/UPLC/SEC, elemental, microbiology, sterility, endotoxin, particulates and stability. CCI/excursion not verified. | K11: Priority laboratory RFI; blind split-sample qualification before use. | L11: Not Started | N11: Not Started | O11: Not Run | P11: Hold
C12: L04 | D12: Intertek Pharmaceutical Services India, Mumbai | E12: India | F12: Tex Centre, Andheri East, Mumbai | G12: 46 | H12: C | I12: Current IAS ISO 17025 scope is environmental, not pharmaceutical; prior NABL scope expired and was non-pharma; claimed MH-FDA approval lacks primary certificate; no FDA site record verified. | J12: Marketing-supported HPLC, LC-MS/MS, GC, ICP, stability and E&L research potential, but required peptide and microbiology methods lack current site-specific regulated scope. | K12: Do not use as sole release lab; RFI only for bounded specialist research pending primary licences/scopes. | L12: Not Started | N12: Not Started | O12: Not Run | P12: Hold
C15: MINIMUM METHOD-QUALIFICATION DOMAINS
C17: Domain | D17: Required evidence
C18: Identity / sequence | D18: LC-MS intact mass and peptide mapping; sequence coverage; orthogonal identity; disulfide/modification confirmation.
C19: Assay / purity | D19: Stability-indicating HPLC/UPLC; related substances; response factors; LOQ; forced degradation and mass balance.
C20: Process residuals | D20: Residual solvents, counter-ion, water, elemental/genotoxic/nitrosamine and resin/linker-derived impurities as applicable.
C21: Micro / sterile | D21: Bioburden, endotoxin, microbial limits, sterility, particulates and method suitability for the exact matrix.
C22: Container / device | D22: CCI, E&L, silicone/tungsten, dose accuracy and component compatibility where relevant.
C23: Stability / excursions | D23: Mapped chambers, alarms, ICH conditions, freeze/thaw, light/heat and temperature-excursion protocol.
C24: Data integrity | D24: Native files, metadata, audit trails, integration history, access roles, backup/restore, OOS/OOT/CAPA and raw-data rights.
C25: Custody / retains | D25: Tamper seals, logger review, receipt checks, LIMS traceability, controlled aliquots, retains and no unapproved subcontracting.

Sheet RFI Tracker
C3: Supplier and Laboratory Due-Diligence RFI Tracker
C5: Controlled request list for product-, site-, batch-, method- and lane-specific qualification
C6: Complete each field; use Unknown / Not Applicable explicitly; high-priority share is intentionally limited
C8: Request ID | D8: Workstream | E8: Detailed Request | F8: Priority | G8: Applies To | H8: Target Entity | I8: Gate | J8: Owner | K8: Status | L8: Date Requested | M8: SLA Days | N8: Due Date | O8: Date Received | P8: Review Outcome | Q8: Evidence Link | R8: Days Outstanding | S8: Notes
C9: RFI-001 | D9: Corporate & Legal | E9: Provide contracting entity, all manufacturing/testing affiliates, corporate numbers, ownership/UBO and authorized signatories. | F9: High | G9: Manufacturers | I9: Pre-audit | K9: Not Started | M9: 10 | N9: =IF(L9="","",L9+M9) | P9: Pending | R9: =IF(OR(K9="Closed",L9=""),"",MAX(0,TODAY()-L9))
C10: RFI-002 | D10: Corporate & Legal | E10: Provide legal title or lease evidence for each proposed site and reconcile every address across licences, FEI, certificates and invoices. | F10: High | G10: Manufacturers & Laboratories | I10: Pre-audit | K10: Not Started | M10: 10 | N10: =IF(L10="","",L10+M10) | P10: Pending | R10: =IF(OR(K10="Closed",L10=""),"",MAX(0,TODAY()-L10))
C11: RFI-003 | D11: Corporate & Legal | E11: Provide current organization charts for corporate, site quality, production, QC, regulatory, supply and pharmacovigilance interfaces. | F11: Medium | G11: Manufacturers & Laboratories | I11: Pre-audit | K11: Not Started | M11: 10 | N11: =IF(L11="","",L11+M11) | P11: Pending | R11: =IF(OR(K11="Closed",L11=""),"",MAX(0,TODAY()-L11))
C12: RFI-004 | D12: Corporate & Legal | E12: Provide audited financial statements, insurance certificates, business-continuity funding and material litigation/sanctions disclosures. | F12: Medium | G12: Manufacturers | I12: Pre-contract | K12: Not Started | M12: 10 | N12: =IF(L12="","",L12+M12) | P12: Pending | R12: =IF(OR(K12="Closed",L12=""),"",MAX(0,TODAY()-L12))
C13: RFI-005 | D13: Corporate & Legal | E13: Declare all brokers, agents, distributors and consultants in the proposed transaction and confirm no therapeutic material is sourced from traders. | F13: High | G13: Manufacturers | I13: No-Go | K13: Not Started | M13: 10 | N13: =IF(L13="","",L13+M13) | P13: Pending | R13: =IF(OR(K13="Closed",L13=""),"",MAX(0,TODAY()-L13))
C14: RFI-006 | D14: Corporate & Legal | E14: Provide anti-bribery, sanctions, export-control, modern-slavery and conflict-of-interest declarations. | F14: Medium | G14: Manufacturers & Laboratories | I14: Pre-contract | K14: Not Started | M14: 10 | N14: =IF(L14="","",L14+M14) | P14: Pending | R14: =IF(OR(K14="Closed",L14=""),"",MAX(0,TODAY()-L14))
C15: RFI-007 | D15: Regulatory & Licences | E15: Provide current local manufacturing/testing licences and every annex for the exact legal entity, address, building, activity and dosage form. | F15: High | G15: Manufacturers & Laboratories | I15: No-Go | K15: Not Started | M15: 10 | N15: =IF(L15="","",L15+M15) | P15: Pending | R15: =IF(OR(K15="Closed",L15=""),"",MAX(0,TODAY()-L15))
C16: RFI-008 | D16: Regulatory & Licences | E16: Provide current GMP/GDP/GLP/ISO certificates and full scope schedules, with issuing-body verification links and expiry/status. | F16: High | G16: Manufacturers & Laboratories | I16: Pre-audit | K16: Not Started | M16: 10 | N16: =IF(L16="","",L16+M16) | P16: Pending | R16: =IF(OR(K16="Closed",L16=""),"",MAX(0,TODAY()-L16))
C17: RFI-009 | D17: Regulatory & Licences | E17: List the last three regulator inspections for each proposed site, including dates, authority, scope, observations, responses, EIR/final classification and commitments. | F17: High | G17: Manufacturers & Laboratories | I17: Pre-audit | K17: Not Started | M17: 10 | N17: =IF(L17="","",L17+M17) | P17: Pending | R17: =IF(OR(K17="Closed",L17=""),"",MAX(0,TODAY()-L17))
C18: RFI-010 | D18: Regulatory & Licences | E18: Disclose all warning letters, import alerts, non-compliance statements, recalls, suspensions, licence restrictions and regulator commitments for ten years. | F18: High | G18: Manufacturers & Laboratories | I18: No-Go | K18: Not Started | M18: 10 | N18: =IF(L18="","",L18+M18) | P18: Pending | R18: =IF(OR(K18="Closed",L18=""),"",MAX(0,TODAY()-L18))
C19: RFI-011 | D19: Regulatory & Licences | E19: Provide evidence of closure and CAPA effectiveness for every public adverse event identified in the George research report. | F19: High | G19: Manufacturers & Laboratories | I19: Pre-contract | K19: Not Started | M19: 10 | N19: =IF(L19="","",L19+M19) | P19: Pending | R19: =IF(OR(K19="Closed",L19=""),"",MAX(0,TODAY()-L19))
C20: RFI-012 | D20: Regulatory & Licences | E20: Provide product-specific CEP, DMF, ASMF, LoA, approved dossier references and current status; distinguish filing from approval. | F20: High | G20: Manufacturers | I20: Pre-audit | K20: Not Started | M20: 10 | N20: =IF(L20="","",L20+M20) | P20: Pending | R20: =IF(OR(K20="Closed",L20=""),"",MAX(0,TODAY()-L20))
... C86: RFI-078 | D86: Laboratory Qualification | E86: Demonstrate successful method transfer/verification and issue a final method/site qualification report with restrictions and requalification triggers. | F86: High | G86: Laboratories | I86: Method Qualification | K86: Not Started | M86: 10 | N86: =IF(L86="","",L86+M86) | P86: Pending | R86: =IF(OR(K86="Closed",L86=""),"",MAX(0,TODAY()-L86))

Sheet 90-Day Plan
C3: Ninety-Day Supplier Qualification Programme
C5: Cross-functional documentary review, technical assessment, audit, laboratory qualification, CAPA and board disposition
C6: No purchase or release while a critical/no-go item remains open
C8: Phase | D8: Timing | E8: Activity | F8: Primary Owner | G8: Inputs | H8: Deliverable | I8: Gate | J8: Status | K8: Target Date | L8: Actual Date | M8: Evidence / Decision Note
C9: 1 | D9: Days 0–10 | E9: Freeze product target profile, dosage form, annual demand, registered-market strategy and evidence requirements; issue NDAs and RFIs. | F9: Project Lead / Regulatory | G9: Target product profile and forecast | H9: Approved requirement and one exact proposed chain per supplier | I9: RFI Approved | J9: Not Started
C10: 2 | D10: Days 11–25 | E10: Verify legal entities, licences, regulator records, dossier references, sanctions/export constraints and adverse-history packages. | F10: Regulatory / Quality / Legal | G10: RFI responses and primary records | H10: Document-completeness score and reject/advance list | I10: Document Gate | J10: Not Started
C11: 3 | D11: Days 26–40 | E11: Review route, scale, PPQ/CPV, impurity strategy, analytical/stability data, cleaning and sterile/device evidence. | F11: Technical / Quality | G11: Technical document room | H11: Product/site technical risk assessment and audit agenda | I11: Technical Gate | J11: Not Started
C12: 4 | D12: Days 41–55 | E12: Assess material genealogy, capacity, subcontractors, BCP, cold chain, South Africa lane and quality-agreement redlines. | F12: Supply / Quality / Commercial | G12: Supplier map, capacity and logistics data | H12: Approved dependency map and preliminary SAHPRA gap assessment | I12: Supply Gate | J12: Not Started
C13: 5 | D13: Days 56–70 | E13: Conduct risk-based on-site audits of proposed API and drug-product sites; review native data and adverse cases. | F13: Lead Auditor / SMEs | G13: Audit plan and document room | H13: Critical/major/other findings and preliminary disposition | I13: Audit Gate | J13: Not Started
C14: 6 | D14: Days 61–78 | E14: Audit laboratories and run blind split-sample method exercise in parallel. | F14: QC / Laboratory Lead | G14: Approved protocol and three lots | H14: Method/site comparability, custody and raw-data assessment | I14: Method Gate | J14: Not Started
C15: 7 | D15: Days 71–85 | E15: Review supplier/laboratory CAPA, close quality/technical agreements and confirm effectiveness plans. | F15: Quality / Legal / Supply | G15: CAPA and agreement redlines | H15: No critical open finding; acceptable owners/dates/effectiveness | I15: CAPA Gate | J15: Not Started
C16: 8 | D16: Days 86–90 | E16: Cross-functional quality, regulatory, supply, legal and commercial decision board; re-score from verified evidence. | F16: Steering Committee | G16: Complete diligence file | H16: Conditional shortlist, hold or no-go with expiry/reassessment date | I16: Board Decision | J16: Not Started
C19: AUDIT SAMPLING MINIMUM
C21: Sample | D21: Audit expectation
C22: Recent release batch | D22: Trace from materials and approved vendors through production, testing, release, storage and distribution.
C23: Deviation or OOS batch | D23: Review original data, hypothesis, root cause, retest/resample, impact, CAPA and recurrence.
C24: Reworked/reprocessed or low-yield batch | D24: Confirm authorization, scientific rationale, impurity impact and dossier consistency.
C25: Stability OOT or complaint case | D25: Review trend rules, escalation, product impact, notification and CAPA.
C26: Cleaning-validation run | D26: Confirm worst case, HBEL, recovery, sampling, shared equipment and continued verification.
C27: Supplier/material change | D27: Trace qualification, comparability, change control, dossier impact and customer approval.
C28: Sterile additions | D28: One failed/aborted APS if any, one EM action event, and one CCI or particulate investigation.

Sheet Risk & No-Go
C3: Supply-Chain Risk Register and No-Go Gates
C5: Risks are product-, site-, method- and lane-specific; numeric score never overrides a no-go condition
C6: Disposition: Monitor / Conditional Hold / No-Go / Closed
C8: Risk ID | D8: Domain | E8: Risk / Failure Mode | F8: Impacted Scope | G8: Likelihood | H8: Impact | I8: Current Evidence | J8: Required Mitigation | K8: Owner | L8: Disposition | M8: Target Date | N8: Evidence / Closure Note
C9: R-001 | D9: Regulatory | E9: No SAHPRA registration, site recognition or dossier linkage established. | F9: All proposed chains | G9: High | H9: Critical | I9: Unknown for every manufacturer. | J9: Commission South African regulatory gap assessment and fix applicant/importer/licence/dossier chain. | K9: Regulatory | L9: Conditional Hold
C10: R-002 | D10: Legal site | E10: Contract, licence, dossier and actual physical site do not match. | F10: Manufacturer or laboratory | G10: Medium | H10: Critical | I10: Public records incomplete for several entities. | J10: Reconcile legal entity, address, building, line, activity and authorized scope. | K10: Legal / Quality | L10: No-Go
C11: R-003 | D11: Data integrity | E11: Native electronic data or audit trails are refused, altered, selectively deleted or incomplete. | F11: All quality decisions | G11: Medium | H11: Critical | I11: Public DI evidence is weak. | J11: Contract raw-data rights; audit systems, roles, metadata, reintegration and backups. | K11: Quality | L11: No-Go
C12: R-004 | D12: Subcontracting | E12: Undisclosed manufacturing, testing, sterilization, device, storage or logistics subcontractor. | F12: All proposed chains | G12: High | H12: Critical | I12: Public subcontract maps are generally absent. | J12: Named schedule, prior approval, audit rights and no further subcontracting. | K12: Quality / Supply | L12: No-Go
C13: R-005 | D13: Raw materials | E13: Critical amino acid, resin/linker, side chain or reagent manufacturer/country cannot be identified. | F13: Peptide API | G13: High | H13: Critical | I13: Origin and dual-source status generally unknown. | J13: Complete genealogy, risk assessment, second-source plan and safety stock. | K13: Supply / Technical | L13: No-Go
C14: R-006 | D14: Single site | E14: Only one validated API or sterile site/train is available. | F14: Most candidates | G14: High | H14: High | I14: Site concentration is widespread. | J14: BCP evidence, alternate-site milestone, transfer rights, buffer stock and RTO. | K14: Supply | L14: Conditional Hold
C15: R-007 | D15: Cold chain | E15: No qualified Asia-to-South-Africa lane or customs-delay simulation. | F15: Temperature-sensitive material | G15: High | H15: Critical | I15: Not publicly evidenced for any candidate. | J15: Seasonal lane qualification, loggers, backup carrier and excursion decision tree. | K15: Logistics / Quality | L15: Conditional Hold
C16: R-008 | D16: Process validation | E16: PPQ/CPV or equipment qualification is incomplete or adverse history is unresolved. | F16: CPC, Piramal and others | G16: Medium | H16: Critical | I16: Public 483/VAI history exists. | J16: Review full inspection packages, PPQ/CPV, CAPA effectiveness and recurrence. | K16: Technical / Quality | L16: Conditional Hold
C17: R-009 | D17: Cleaning | E17: Shared-equipment carryover/cleaning validation is inadequate. | F17: Multi-product API sites | G17: Medium | H17: Critical | I17: Specific FDA concern at Piramal/CPC-related histories. | J17: HBEL-based cleaning validation, worst-case selection and ongoing verification. | K17: Quality | L17: No-Go
C18: R-010 | D18: Sterility assurance | E18: CCS, APS, EM, sterilization/depyrogenation, CCI or particle evidence is inadequate. | F18: Sterile finished dose | G18: Medium | H18: Critical | I18: Public sterile evidence incomplete. | J18: Separate sterile-site audit and full assurance package. | K18: Sterile SME | L18: No-Go
C19: R-011 | D19: Device chain | E19: Component makers, assembly site, dose accuracy or complaint interface are opaque. | F19: PFS/pen/autoinjector | G19: High | H19: High | I19: Hybio/Scino device chains require disclosure. | J19: Map components and responsibilities; verify device/combination-product controls. | K19: Device SME | L19: Conditional Hold
C20: R-012 | D20: Laboratory scope | E20: Accreditation or licence does not cover the exact site/method/matrix. | F20: Independent testing | G20: High | H20: Critical | I20: All four labs have scope gaps; Intertek current scope is non-pharma. | J20: Obtain full scope annex, audit and method-by-method qualification. | K20: QC Lead | L20: Conditional Hold
... C28: R-020 | D28: Traceability | E28: Recall, returns, quarantine or shipment traceability cannot identify every batch and handoff. | F28: South Africa distribution | G28: Medium | H28: Critical | I28: No candidate SA lane tested. | J28: End-to-end mock recall and shipment trace before first commercial supply. | K28: Quality / Logistics | L28: Conditional Hold

Sheet Source Register
C3: Research Source Register
C5: Complete source inventory extracted from discovery, ten manufacturer dossiers and four laboratory dossiers
C6: 301 unique URLs | Access and content may change; archive primary evidence in the controlled data room
C8: Source ID | D8: Category | E8: Entity / Dossier | F8: Source File | G8: URL | H8: Review Cutoff | I8: Evidence Note
C9: SRC-001 | D9: Discovery | E9: Discovery universe | F9: /home/ubuntu/george_asia_peptide_due_diligence/discovery.md | G9: https://www.fda.gov/drugs/drug-approvals-and-databases/drug-establishments-current-registration-site-decrs | H9: 20 August 2026 | I9: See cited dossier/report; issuer claims require primary-record verification where identified.
C10: SRC-002 | D10: Discovery | E10: Discovery universe | F10: /home/ubuntu/george_asia_peptide_due_diligence/discovery.md | G10: https://tides.wuxiapptec.com/ | H10: 20 August 2026 | I10: See cited dossier/report; issuer claims require primary-record verification where identified.
C11: SRC-003 | D11: Discovery | E11: Discovery universe | F11: /home/ubuntu/george_asia_peptide_due_diligence/discovery.md | G11: https://tides.wuxiapptec.com/wuxi-apptecs-changzhou-and-taixing-api-sites-successfully-pass-fda-inspections/ | H11: 20 August 2026 | I11: See cited dossier/report; issuer claims require primary-record verification where identified.
C12: SRC-004 | D12: Discovery | E12: Discovery universe | F12: /home/ubuntu/george_asia_peptide_due_diligence/discovery.md | G12: https://www.sinopep.com/quotation/gmp-peptides/ | H12: 20 August 2026 | I12: See cited dossier/report; issuer claims require primary-record verification where identified.
C13: SRC-005 | D13: Discovery | E13: Discovery universe | F13: /home/ubuntu/george_asia_peptide_due_diligence/discovery.md | G13: https://www.fda.gov/media/190915/download | H13: 20 August 2026 | I13: See cited dossier/report; issuer claims require primary-record verification where identified.
C14: SRC-006 | D14: Discovery | E14: Discovery universe | F14: /home/ubuntu/george_asia_peptide_due_diligence/discovery.md | G14: https://www.fda.gov/media/183518/download | H14: 20 August 2026 | I14: See cited dossier/report; issuer claims require primary-record verification where identified.
C15: SRC-007 | D15: Discovery | E15: Discovery universe | F15: /home/ubuntu/george_asia_peptide_due_diligence/discovery.md | G15: https://www.hybio.com/about-us/ | H15: 20 August 2026 | I15: See cited dossier/report; issuer claims require primary-record verification where identified.
C16: SRC-008 | D16: Discovery | E16: Discovery universe | F16: /home/ubuntu/george_asia_peptide_due_diligence/discovery.md | G16: https://www.fda.gov/media/148286/download | H16: 20 August 2026 | I16: See cited dossier/report; issuer claims require primary-record verification where identified.
C17: SRC-009 | D17: Discovery | E17: Discovery universe | F17: /home/ubuntu/george_asia_peptide_due_diligence/discovery.md | G17: https://cpcscientific.com/custom-peptide-synthesis/cgmp-peptide-manufacturing/ | H17: 20 August 2026 | I17: See cited dossier/report; issuer claims require primary-record verification where identified.
C18: SRC-010 | D18: Discovery | E18: Discovery universe | F18: /home/ubuntu/george_asia_peptide_due_diligence/discovery.md | G18: https://www.fda.gov/media/178556/download | H18: 20 August 2026 | I18: See cited dossier/report; issuer claims require primary-record verification where identified.
C19: SRC-011 | D19: Discovery | E19: Discovery universe | F19: /home/ubuntu/george_asia_peptide_due_diligence/discovery.md | G19: https://www.fda.gov/media/181469/download | H19: 20 August 2026 | I19: See cited dossier/report; issuer claims require primary-record verification where identified.
... C309: SRC-301 | D309: Laboratory | E309: 04-L04 | F309: /home/ubuntu/george_asia_peptide_due_diligence/laboratories/04-L04.md | G309: https://www.sahpra.org.za/wp-content/uploads/2022/09/SAHPGL-INSP-04_v5Guidelines-for-Preparation-of-Site-Master-File.pdf | H309: 20 August 2026 | I309: See cited dossier/report; issuer claims require primary-record verification where identified.
